char_counter/__init__.py
char_counter/char_counter.py
cli/__init__.py
cli/parser.py
tests/__init__.py
tests/test_parser.py
char_counter_le0bu-0.0.2.dist-info/METADATA
char_counter_le0bu-0.0.2.dist-info/WHEEL
char_counter_le0bu-0.0.2.dist-info/entry_points.txt
char_counter_le0bu-0.0.2.dist-info/licenses/LICENSE
char_counter_le0bu-0.0.2.dist-info/RECORD
