Metadata-Version: 2.3
Name: char_counter_Le0Bu
Version: 0.0.2
Summary: Simple program that counts the number of characters that occur only once in a string. Works through the command-line interface.
Author-email: Leo Bu <burimko@gmail.com>
License: Copyright (c) 2018 The Python Packaging Authority
License-File: LICENSE
Requires-Python: >=3.12
